mpsiem_api/__init__.py
mpsiem_api/__version__.py
mpsiem_api/base_functions/__init__.py
mpsiem_api/base_functions/base.py
mpsiem_api/modules/__init__.py
mpsiem_api/modules/core.py
mpsiem_api/modules/events.py
mpsiem_api/modules/siem_auth.py
mpsiem_api/params/__init__.py
mpsiem_api/params/interfaces.py
mpsiem_api/params/params.py
mpsiem_api-0.0.2.dist-info/LICENSE
mpsiem_api-0.0.2.dist-info/METADATA
mpsiem_api-0.0.2.dist-info/WHEEL
mpsiem_api-0.0.2.dist-info/top_level.txt
mpsiem_api-0.0.2.dist-info/RECORD
