Metadata-Version: 2.1
Name: mpsiem-api
Version: 0.0.2
Summary: Basic MaxPatrol SIEM API wrapper
Home-page: https://github.com/aw350m33d/mpsiem_api
Author: Kirill Kiryanov, Anton Kutepov
Author-email: 
License: UNKNOWN
Project-URL: Bug Tracker, https://github.com/aw350m33d/mpsiem_api/issues
Platform: UNKNOWN
Classifier: Programming Language :: Python :: 3
Classifier: License :: OSI Approved :: MIT License
Classifier: Operating System :: OS Independent
Requires-Python: >=3.6
Requires-Dist: requests
Requires-Dist: jinja2
